kloom_litellm/__init__.py
kloom_litellm/plugin.py
kloom_litellm-0.0.1.dist-info/LICENSE
kloom_litellm-0.0.1.dist-info/METADATA
kloom_litellm-0.0.1.dist-info/NOTICE
kloom_litellm-0.0.1.dist-info/WHEEL
kloom_litellm-0.0.1.dist-info/top_level.txt
kloom_litellm-0.0.1.dist-info/RECORD
