Metadata-Version: 2.1
Name: kloom-litellm
Version: 0.0.1
Summary: A LiteLLM plugin for intelligent model routing and request tracking with Kloom
Author-email: Kloom <support@kloom.ai>
Maintainer-email: Kloom <support@kloom.ai>
License: Apache License 2.0
Project-URL: Homepage, https://kloom.ai
Project-URL: Documentation, https://docs.kloom.ai/quickstart/litellm
Project-URL: Repository, https://github.com/kloom-ai/kloom-litellm-plugin
Project-URL: Issues, https://github.com/kloom-ai/kloom-litellm-plugin/issues
Keywords: litellm,llm,ai,kloom,model-routing,observability,logging,openai,anthropic
Classifier: Development Status :: 3 - Alpha
Classifier: Intended Audience :: Developers
Classifier: Programming Language :: Python :: 3
Classifier: Programming Language :: Python :: 3.9
Classifier: Programming Language :: Python :: 3.10
Classifier: Programming Language :: Python :: 3.11
Classifier: Programming Language :: Python :: 3.12
Classifier: Programming Language :: Python :: 3.13
Classifier: Topic :: Software Development :: Libraries :: Python Modules
Classifier: Topic :: Scientific/Engineering :: Artificial Intelligence
Requires-Python: >=3.9
License-File: LICENSE
License-File: NOTICE
Requires-Dist: litellm>=1.79.3
Requires-Dist: httpx>=0.27.0
